azure/mgmt/nginx/__init__.py
azure/mgmt/nginx/_configuration.py
azure/mgmt/nginx/_nginx_management_client.py
azure/mgmt/nginx/_patch.py
azure/mgmt/nginx/_serialization.py
azure/mgmt/nginx/_vendor.py
azure/mgmt/nginx/_version.py
azure/mgmt/nginx/py.typed
azure/mgmt/nginx/aio/__init__.py
azure/mgmt/nginx/aio/_configuration.py
azure/mgmt/nginx/aio/_nginx_management_client.py
azure/mgmt/nginx/aio/_patch.py
azure/mgmt/nginx/aio/operations/__init__.py
azure/mgmt/nginx/aio/operations/_certificates_operations.py
azure/mgmt/nginx/aio/operations/_configurations_operations.py
azure/mgmt/nginx/aio/operations/_deployments_operations.py
azure/mgmt/nginx/aio/operations/_operations.py
azure/mgmt/nginx/aio/operations/_patch.py
azure/mgmt/nginx/models/__init__.py
azure/mgmt/nginx/models/_models_py3.py
azure/mgmt/nginx/models/_nginx_management_client_enums.py
azure/mgmt/nginx/models/_patch.py
azure/mgmt/nginx/operations/__init__.py
azure/mgmt/nginx/operations/_certificates_operations.py
azure/mgmt/nginx/operations/_configurations_operations.py
azure/mgmt/nginx/operations/_deployments_operations.py
azure/mgmt/nginx/operations/_operations.py
azure/mgmt/nginx/operations/_patch.py
azure_mgmt_nginx-3.0.0.dist-info/LICENSE
azure_mgmt_nginx-3.0.0.dist-info/METADATA
azure_mgmt_nginx-3.0.0.dist-info/WHEEL
azure_mgmt_nginx-3.0.0.dist-info/top_level.txt
azure_mgmt_nginx-3.0.0.dist-info/RECORD
